DESCRIPTION.rst
MANIFEST.in
README.rst
setup.py
pypermedia/__init__.py
pypermedia/client.py
pypermedia/gzip_requests.py
pypermedia/siren.py
pypermedia.egg-info/PKG-INFO
pypermedia.egg-info/SOURCES.txt
pypermedia.egg-info/dependency_links.txt
pypermedia.egg-info/requires.txt
pypermedia.egg-info/top_level.txt
tests/__init__.py
tests/test_siren.py
tests/unit/__init__.py
tests/unit/test_client.py
tests/unit/test_siren.py