Metadata-Version: 1.1
Name: pypermedia
Version: 0.4.2
Summary: Python client for hypermedia APIs.
Home-page: UNKNOWN
Author: Alex Maskovyak
Author-email: alex.maskovyak@vertical-knowledge.com
License: GPLv2
Keywords: c,l,i,e,n,t, ,r,e,s,t, ,h,y,p,e,r,m,e,d,i,a, ,h,t,t,p, ,p,r,o,x,y, ,s,i,r,e,n, ,a,p,i, ,h,a,t,e,o,a,s
Platform: UNKNOWN
Classifier: Development Status :: 4 - Beta
Classifier: Intended Audience :: Developers
Classifier: Topic :: Software Development :: Libraries :: Python Modules
Classifier: License :: OSI Approved :: GNU General Public License v2 (GPLv2)
Classifier: Programming Language :: Python :: 2.7
Classifier: Programming Language :: Python :: 3.3
